axaremote/__init__.py
axaremote/__main__.py
axaremote/axaconnection.py
axaremote/axaremote.py
axaremote/py.typed
axaremote-0.0.6.dist-info/LICENSE
axaremote-0.0.6.dist-info/METADATA
axaremote-0.0.6.dist-info/WHEEL
axaremote-0.0.6.dist-info/top_level.txt
axaremote-0.0.6.dist-info/RECORD
