Metadata-Version: 2.1
Name: axaremote
Version: 0.0.6
Summary: Library to control AXA Remote window openers.
Author: Rogier van Staveren
License: Apache-2.0
Project-URL: Homepage, https://github.com/rrooggiieerr/axaremote.py
Project-URL: Bug Tracker, https://github.com/rrooggiieerr/axaremote.py/issues
Classifier: Programming Language :: Python :: 3
Classifier: Intended Audience :: Developers
Classifier: License :: OSI Approved :: Apache Software License
Classifier: Operating System :: OS Independent
Requires-Python: >=3.7
License-File: LICENSE
Requires-Dist: pyserial >=3.4
Requires-Dist: telnetlib3 >=2.0.4
